odoo/addons/hr_employee_health/README.rst
odoo/addons/hr_employee_health/__init__.py
odoo/addons/hr_employee_health/__manifest__.py
odoo/addons/hr_employee_health/data/data_blood_type.xml
odoo/addons/hr_employee_health/data/data_health_condition_severity.xml
odoo/addons/hr_employee_health/data/data_health_condition_type.xml
odoo/addons/hr_employee_health/i18n/es.po
odoo/addons/hr_employee_health/i18n/fr.po
odoo/addons/hr_employee_health/i18n/hr_employee_health.pot
odoo/addons/hr_employee_health/i18n/it.po
odoo/addons/hr_employee_health/models/__init__.py
odoo/addons/hr_employee_health/models/hr_employee.py
odoo/addons/hr_employee_health/models/hr_employee_blood_type.py
odoo/addons/hr_employee_health/models/hr_employee_health_condition.py
odoo/addons/hr_employee_health/models/hr_employee_health_condition_severity.py
odoo/addons/hr_employee_health/models/hr_employee_health_condition_type.py
odoo/addons/hr_employee_health/readme/CONTRIBUTORS.rst
odoo/addons/hr_employee_health/readme/DESCRIPTION.rst
odoo/addons/hr_employee_health/security/ir.model.access.csv
odoo/addons/hr_employee_health/static/description/icon.png
odoo/addons/hr_employee_health/static/description/index.html
odoo/addons/hr_employee_health/tests/__init__.py
odoo/addons/hr_employee_health/views/hr_employee.xml
odoo/addons/hr_employee_health/views/hr_employee_health_condition.xml
odoo14_addon_hr_employee_health-14.0.1.0.0.dist-info/METADATA
odoo14_addon_hr_employee_health-14.0.1.0.0.dist-info/WHEEL
odoo14_addon_hr_employee_health-14.0.1.0.0.dist-info/top_level.txt
odoo14_addon_hr_employee_health-14.0.1.0.0.dist-info/RECORD
